big_integer/__init__.py
big_integer/big_integer.py
simple_big_integer_pypi-0.1.dist-info/LICENSE
simple_big_integer_pypi-0.1.dist-info/METADATA
simple_big_integer_pypi-0.1.dist-info/WHEEL
simple_big_integer_pypi-0.1.dist-info/top_level.txt
simple_big_integer_pypi-0.1.dist-info/RECORD
