Metadata-Version: 2.1
Name: simple-big-integer-pypi
Version: 0.1
Summary: A Python package for handling big integers
Home-page: https://github.com/0xNomind/simple-big-integer-pypi
Author: 0xNomind
Author-email: nomind.crypto@gmail.com
Classifier: License :: OSI Approved :: MIT License
Classifier: Programming Language :: Python :: 3
Classifier: Programming Language :: Python :: 3.6
Classifier: Programming Language :: Python :: 3.7
Classifier: Programming Language :: Python :: 3.8
Classifier: Programming Language :: Python :: 3.9
License-File: LICENSE
